LICENSE
MANIFEST.in
README.md
setup.py
br_feriados.egg-info/PKG-INFO
br_feriados.egg-info/SOURCES.txt
br_feriados.egg-info/dependency_links.txt
br_feriados.egg-info/requires.txt
br_feriados.egg-info/top_level.txt
init/__init__.py